pica/__init__.py
pica/_stash.py
picapica-0.1.2.dist-info/licenses/LICENSE
picapica-0.1.2.dist-info/METADATA
picapica-0.1.2.dist-info/WHEEL
picapica-0.1.2.dist-info/top_level.txt
picapica-0.1.2.dist-info/RECORD
