Metadata-Version: 2.4
Name: picapica
Version: 0.1.2
Summary: A tiny persistent key–value store built on SQLite.
Author: Michael Dunne
License-Expression: MIT
Project-URL: Homepage, https://github.com/mpdunne/pica
Requires-Python: >=3.9
License-File: LICENSE
Dynamic: license-file
